{
    "scenes": [
        {
            "objects": [
                {
                    "color": [
                        1.0,
                        1.0,
                        1.0,
                        1.0
                    ],
                    "enableLighting": true,
                    "meshVertexCounts": [
                        144
                    ],
                    "modelFileName": "anchor.obj",
                    "modelTextureHandles": [
                        1
                    ],
                    "name": "anchor[2]",
                    "position": [
                        0.0,
                        0.0,
                        -1.0235810279846191
                    ],
                    "rotation": [
                        0.0,
                        -0.0,
                        0.0
                    ],
                    "scale": [
                        1.0,
                        1.0,
                        1.0
                    ],
                    "scriptFileName": "Move.lua",
                    "type": "Model"
                },
                {
                    "color": [
                        1.0,
                        1.0,
                        1.0,
                        1.0
                    ],
                    "enableLighting": true,
                    "meshVertexCounts": [
                        144
                    ],
                    "modelFileName": "anchor.obj",
                    "modelTextureHandles": [
                        1
                    ],
                    "name": "anchor[3]",
                    "position": [
                        1.2995535135269165,
                        0.0,
                        0.0
                    ],
                    "rotation": [
                        0.0,
                        -0.0,
                        0.0
                    ],
                    "scale": [
                        1.0,
                        1.0,
                        1.0
                    ],
                    "scriptFileName": "",
                    "type": "Model"
                }
            ],
            "sceneName": "LastScriptRunScene.json"
        }
    ]
}